LICENSE
MANIFEST.in
README.md
requirements.txt
setup.py
redis_cache/__init__.py
redis_cache/rediscache.py
redis_cache/test_rediscache.py
redis_simple_cache.egg-info/PKG-INFO
redis_simple_cache.egg-info/SOURCES.txt
redis_simple_cache.egg-info/dependency_links.txt
redis_simple_cache.egg-info/requires.txt
redis_simple_cache.egg-info/top_level.txt