Metadata-Version: 1.1
Name: redis-simple-cache
Version: 0.0.5
Summary: redis-simple-cache is a pythonic interface for creating a cache over redis. It provides simple decorators that can be added to any function to cache its return values. 
Home-page: https://github.com/vivekn/redis-simple-cache
Author: Vivek Narayanan, Flávio Juvenal, Sam Zaydel
Author-email: flaviojuvenal@gmail.com
License: 3-clause BSD
Keywords: decorator decorators redis cache
Platform: UNKNOWN
Classifier: Development Status :: 3 - Alpha
Classifier: Topic :: Utilities
Classifier: License :: OSI Approved :: BSD License
